Final_Project/Registration.py
Final_Project/__init__.py
Final_Project/__main__.py
Final_Project/build_face_dataset.py
Final_Project/designer_app.py
Final_Project/dialog.py
Final_Project/extract_embeddings1.py
Final_Project/main_app2.py
Final_Project/openface_nn4.small2.v1.t7
Final_Project/recognize_video1.py
Final_Project/startApp.py
Final_Project/train_model1.py
Final_Project/attendance_records/__init__.py
Final_Project/changes/__init__.py
Final_Project/changes/dataset/__init__.py
Final_Project/changes/dataset/unknown/__init__.py
Final_Project/changes/dataset/unknown/alan_grant.jpg
Final_Project/changes/dataset/unknown/claire_dearing.jpg
Final_Project/changes/dataset/unknown/ellie_sattler.jpg
Final_Project/changes/dataset/unknown/ian_malcolm.jpg
Final_Project/changes/dataset/unknown/john_hammond.jpg
Final_Project/changes/dataset/unknown/own_grady.jpg
Final_Project/constants/__init__.py
Final_Project/constants/deploy.prototxt
Final_Project/constants/deploy.prototxt.txt
Final_Project/constants/res10_300x300_ssd_iter_140000.caffemodel
Final_Project/files/__init__.py
Final_Project/images/__init__.py
Final_Project/images/new_user_icon.png
Final_Project/output/__init__.py
CAMSyFReT-1.1.1.dist-info/LICENSE
CAMSyFReT-1.1.1.dist-info/METADATA
CAMSyFReT-1.1.1.dist-info/WHEEL
CAMSyFReT-1.1.1.dist-info/entry_points.txt
CAMSyFReT-1.1.1.dist-info/top_level.txt
CAMSyFReT-1.1.1.dist-info/RECORD
