Metadata-Version: 2.1
Name: CAMSyFReT
Version: 1.1.1
Summary: A class Attendance Management System Using Face Recognition Technology
Home-page: https://github.com/The-Professor99/CAMSyFReT
Author: Eze Ihechi Festus
Author-email: festusihechi99@gmail.com
License: MIT
Project-URL: Author Website, https://ihechifestus9.web.app
Project-URL: Source Code, https://github.com/The-Professor99/CAMSyFReT
Keywords: class attendance management system face recognition technology opencv
Requires-Python: >=3.8
License-File: LICENSE
Requires-Dist: imutils (==0.5.4)
Requires-Dist: joblib (==1.1.0)
Requires-Dist: numpy (==1.22.4)
Requires-Dist: opencv-python (==4.6.0.66)
Requires-Dist: pandas (==1.5.0)
Requires-Dist: pkg-resources (==0.0.0)
Requires-Dist: PyQt6 (==6.3.1)
Requires-Dist: PyQt6-Qt6 (==6.3.2)
Requires-Dist: PyQt6-sip (==13.4.0)
Requires-Dist: python-dateutil (==2.8.2)
Requires-Dist: pytz (==2021.3)
Requires-Dist: scikit-learn (==1.0.1)
Requires-Dist: scipy (==1.7.2)
Requires-Dist: six (==1.16.0)
Requires-Dist: threadpoolctl (==3.0.0)
